hotblast/Search.py
hotblast/__init__.py
hotblast/initialize.py
hotblast-0.0.3.dist-info/LICENSE
hotblast-0.0.3.dist-info/METADATA
hotblast-0.0.3.dist-info/WHEEL
hotblast-0.0.3.dist-info/entry_points.txt
hotblast-0.0.3.dist-info/top_level.txt
hotblast-0.0.3.dist-info/RECORD
