Metadata-Version: 2.1
Name: hotblast
Version: 0.0.3
Summary: 一个轻型搜索工具。
Home-page: https://gitee.com/huang-hongzhe/prioritization
Author: 黄宏哲
Author-email: 2528104776@qq.com
License: UNKNOWN
Platform: UNKNOWN
Classifier: Programming Language :: Python :: 3
Classifier: License :: OSI Approved :: MIT License
Classifier: Operating System :: OS Independent
Requires-Python: >=3.6
License-File: LICENSE
